btext/__init__.py
btext/core.py
btext/utill.py
btext-1.0.dist-info/LICENSE.txt
btext-1.0.dist-info/METADATA
btext-1.0.dist-info/WHEEL
btext-1.0.dist-info/top_level.txt
btext-1.0.dist-info/RECORD
