Metadata-Version: 2.1
Name: btext
Version: 1.0
Summary: Bear Au Jus Text (btext) is a tool used for processing a text/string, optimized for data science and data analytics. btext can also implemented with pandas dataframe.
Home-page: https://github.com/haryobagas/btext
Author: Bear Au Jus - ジュースとくま
Author-email: haryobagasasyafah6@gmail.com
License: MIT
Keywords: btext,bearaujus,bearaujus btext,basic string,text procesing,text cleaning,text normalization,text lemming,string procesing,string cleaning,string normalization,string lemming,text procesing in pandas,text cleaning in pandas,text normalization in pandas,text lemming in pandas,string procesing in pandas,string cleaning in pandas,string normalization in pandas,string lemming in pandas,data analysis,data cleaning,data science,data analysis in pandas,data cleaning in pandas,data science in 
Platform: UNKNOWN
Classifier: Development Status :: 5 - Production/Stable
Classifier: Intended Audience :: Developers
Classifier: Operating System :: OS Independent
Classifier: License :: OSI Approved :: MIT License
Classifier: Programming Language :: Python :: 3.7
Classifier: Natural Language :: English
Classifier: Topic :: Utilities
Requires-Dist: textcleaner
